scpert/ProcePertdata.py
scpert/__init__.py
scpert/data_utils.py
scpert/infer.py
scpert/inference.py
scpert/model.py
scpert/predict.py
scpert/scpert.py
scpert/train.py
scpert/train_model.py
scpert/utils.py
scpert-0.1.1.dist-info/LICENSE
scpert-0.1.1.dist-info/METADATA
scpert-0.1.1.dist-info/WHEEL
scpert-0.1.1.dist-info/entry_points.txt
scpert-0.1.1.dist-info/top_level.txt
scpert-0.1.1.dist-info/RECORD
