Metadata-Version: 2.1
Name: scpert
Version: 0.1.1
Summary: Single-cell perturbation modeling toolkit
Home-page: https://github.com/AI4VirtualCell/scPert
Author: AI4VirualCell
Author-email: younanxin@zju.edu.cn
License: UNKNOWN
Platform: UNKNOWN
Classifier: Programming Language :: Python :: 3
Classifier: License :: OSI Approved :: MIT License
Classifier: Operating System :: OS Independent
Requires-Python: >=3.8
Requires-Dist: anndata (==0.9.2)
Requires-Dist: scanpy (==1.9.8)
Requires-Dist: torch (==2.3.0)
Requires-Dist: torch-geometric (==2.6.1)
Requires-Dist: scvi-tools (==0.20.3)
Requires-Dist: pandas (==2.0.3)
Requires-Dist: numpy (==1.24.4)
Requires-Dist: scipy (==1.10.1)
Requires-Dist: cell-gears (==0.0.2)
Requires-Dist: nvidia-cublas-cu12 (==12.1.3.1)
Requires-Dist: nvidia-cudnn-cu12 (==8.9.2.26)
Requires-Dist: flash-attn (==0.2.8)
